unladen_swallow/__init__.py
unladen_swallow/unladen_swallow.py
UnladenSwallow-0.2.1.dist-info/LICENSE
UnladenSwallow-0.2.1.dist-info/METADATA
UnladenSwallow-0.2.1.dist-info/WHEEL
UnladenSwallow-0.2.1.dist-info/top_level.txt
UnladenSwallow-0.2.1.dist-info/RECORD
