Metadata-Version: 2.1
Name: UnladenSwallow
Version: 0.2.1
Summary: This package returns the airspeed velocity of an unladen swallow.
Home-page: https://unladen-swallow.readthedocs.io/en/latest/
Author: Karl Saint Lucy
Author-email: karl@karlsaintlucy.com
License: BSD
Keywords: monty python unladen swallow airspeed velocity
Platform: UNKNOWN
Requires-Dist: Sphinx
